mdcleaner/__init__.py
mdcleaner/cleaner.py
mdcleaner-0.1.4.1.dist-info/LICENSE.txt
mdcleaner-0.1.4.1.dist-info/METADATA
mdcleaner-0.1.4.1.dist-info/WHEEL
mdcleaner-0.1.4.1.dist-info/top_level.txt
mdcleaner-0.1.4.1.dist-info/RECORD
