Metadata-Version: 2.1
Name: mdcleaner
Version: 0.1.4.1
Summary: A utility to clean and convert MD files to ASCII.
Author: Devon White
Author-email: devon.white@signalwire.com
License: MIT
Keywords: markdown cleaner ASCII
Requires-Python: >=3.6
License-File: LICENSE.txt
Requires-Dist: chardet
Requires-Dist: unidecode
